{
    "display": {
        "title": {
            "translate": "jeg.advancements.gunmetal_nugget.title"
        },
        "description": {
            "translate": "jeg.advancements.gunmetal_nugget.description"
        },
        "icon": {
            "item": "jeg:gunmetal_nugget"
        },
        "frame": "task",
        "show_toast": true,
        "announce_to_chat": true,
        "hidden": false
    },
    "criteria": {
        "Item": {
            "trigger": "minecraft:inventory_changed",
            "conditions": {
                "items": [
                    {
                        "items": [
                            "jeg:gunmetal_nugget"
                        ]
                    }
                ]
            }
        }
    },
    "requirements": [
        [
          "Item"
        ]
      ],
    "parent": "jeg:gunmetal_grit"
}